BloomTechLib/__init__.py
BloomTechLib/Analysis/__init__.py
BloomTechLib/Analysis/csv_similarity.py
BloomTechLib/Analysis/examples.py
BloomTechLib/DataBaseOps/__init__.py
BloomTechLib/DataBaseOps/html_to_df.py
BloomTechLib/DataBaseOps/mongo.py
BloomTechLib/DataBaseOps/sql.py
BloomTechLib-0.0.1.dist-info/LICENSE
BloomTechLib-0.0.1.dist-info/METADATA
BloomTechLib-0.0.1.dist-info/WHEEL
BloomTechLib-0.0.1.dist-info/top_level.txt
BloomTechLib-0.0.1.dist-info/RECORD
