Metadata-Version: 2.1
Name: BloomTechLib
Version: 0.0.1
Summary: Python Library of General Data Science Solutions
Home-page: UNKNOWN
Author: Robert Sharp - BloomTech Labs
Author-email: webmaster@sharpdesigndigital.com
License: MIT License
Keywords: BloomTech,Data Science
Platform: UNKNOWN
Classifier: Development Status :: 3 - Alpha
Classifier: Programming Language :: Python :: 3.8
Classifier: Topic :: Software Development :: Libraries :: Python Modules
Requires-Python: >=3.6
Requires-Dist: setuptools (~=50.0.0)
Requires-Dist: pandas (~=1.2.3)
Requires-Dist: psycopg2-binary (~=2.9)
Requires-Dist: python-dotenv (~=0.17.1)
Requires-Dist: pymongo (~=3.11.4)
Requires-Dist: requests (~=2.25.1)
Requires-Dist: dnspython (~=2.1.0)
